<uiConf version="1.0.8_trunk"><overrides> 		<mediaClips> 			<librarySort> 				<clipsVisual visible="0"><sortBy> 					<type>number</type> 					<field>duration</field> 					<showName>CLIP LENGTH</showName></sortBy><sortBy> 					<type>number</type> 					<field>createdAtAsInt</field> 					<showName>CREATION DATE</showName></sortBy><sortBy> 					<type>string</type> 					<field>entryName</field> 					<showName>CLIP NAME</showName></sortBy></clipsVisual> 				<clipsAudio visible="0"><sortBy> 					<type>number</type> 					<field>duration</field> 					<showName>CLIP LENGTH</showName></sortBy><sortBy> 					<type>number</type> 					<field>createdAtAsInt</field> 					<showName>CREATION DATE</showName></sortBy><sortBy> 					<type>string</type> 					<field>entryName</field> 					<showName>CLIP NAME</showName></sortBy></clipsAudio></librarySort> 			<libraryFilter> 				<clipsVisual visible="1"> 				<filterBy> 					<type>none</type> 					<showName>View All</showName></filterBy><filterBy> 					<field>mediaType</field> 					<value>2</value> 					<type>mediaType</type> 					<showName>Video Only</showName></filterBy><filterBy> 					<field>mediaType</field> 					<value>4</value> 					<type>mediaType</type> 					<showName>Photos Only</showName></filterBy></clipsVisual> 				<clipsAudio visible="0"><filterBy> 					<type>none</type> 					<showName>SHOW ALL</showName></filterBy><filterBy> 					<field>adminTags</field> 					<value>music</value> 					<type>tags</type> 					<showName>MUSIC</showName></filterBy><filterBy> 					<field>tags</field> 					<value>voice</value> 					<type>tags</type> 					<showName>RECORDINGS</showName></filterBy> 					<filterBy> 						<field>adminTags</field> 						<value>sound effects</value> 						<type>tags</type> 						<showName>SOUND FX</showName></filterBy></clipsAudio></libraryFilter> 			<mediaTypes> 				<mediaType> 					<typeId>SOLID</typeId> 					<defaultColor>#00f00f</defaultColor> 					<defaultDuration>2</defaultDuration> 					<showInMediaClips>1</showInMediaClips> 					</mediaType> 				<mediaType> 					<typeId>SILENCE</typeId> 					<defaultDuration>2</defaultDuration> 					<showInMediaClips>1</showInMediaClips> 				</mediaType> 				<mediaType> 					<typeId>TRANSITION</typeId><defaultTransitionId>None</defaultTransitionId><defaultDuration>2</defaultDuration><transitionsClearRoughcut>0</transitionsClearRoughcut> 					<defaultTransitionCross>0</defaultTransitionCross></mediaType><mediaType> 					<typeId>IMAGE</typeId> 					<defaultDuration>4</defaultDuration> 					</mediaType> 				<defaultMaxStaticTypesDuration>30</defaultMaxStaticTypesDuration> 				<defaultMinStaticTypesDuration>0.25</defaultMinStaticTypesDuration><defaultMinStreamingTypesDuration>0.25</defaultMinStreamingTypesDuration> 				</mediaTypes></mediaClips> 		<uiElements> 			<removeElements/></uiElements> 		<publishSettings>   			<postPublishWindow show="1"><showPostPublishAlert>0</showPostPublishAlert> 				<thumbnailSettings><width>640</width><height>480</height><quality>90</quality></thumbnailSettings></postPublishWindow></publishSettings></overrides><uIConfigList> 		<uIConfig> 			<cvf> 				<pluginsDirectory>/flash/kae/v1.2/swf/plugins/cvesdk</pluginsDirectory> 				<mediaServerUrl>rtmp://{DOMAIN_NAME}/oflaDemo</mediaServerUrl> 				<pluginsProvider>/flash/kae/v1.2/swf/plugins/cvesdk/plugins.xml</pluginsProvider></cvf> 			<target>KalturaAdvancedVideoEditor.swf</target> 			<cssUrl>/content/uiconf/kaltura/generic/kae_1.2.3/kae_generic_generic_styles.swf?r=2</cssUrl> 			<localeUrl>/content/uiconf/kaltura/generic/kae_1.2/en_US_KalturaAdvancedVideoEditor.swf?r=0</localeUrl> 			<baseLocaleUrl>/content/uiconf/kaltura/generic/kae_1.2/kae_generic_en_US.swf?r=0</baseLocaleUrl></uIConfig> 	</uIConfigList><extraData> 		<contributionWizard> 			<uIConfigId>2891902</uIConfigId> 		</contributionWizard> 	</extraData><screens> 		<helpWindowUrl>/content/uiconf/kaltura/generic/kae_1.2/KAE_Help.png</helpWindowUrl></screens><javaScript enableJSCallbacks="1" enableStatisticsCallbacks="1" enableErrorCallbacks="1" verbose="0"> 		<jsBlock> 			<blockId>publishHandler</blockId><jsHandler>afterPublishHandler</jsHandler><jsfunction/><!--a function to call the container when the user published the roughcut or clicked the close button to nabigate away from the editor. the function get an object with 3 params, first (modified) indicates if there was a change to the roughcut, the second (saved) indicates if the user saved the last changes he made or not.--> 		</jsBlock> 	<jsBlock> 			<blockId>closeHandler</blockId><jsHandler>closeEditorHandler</jsHandler><jsfunction/><!--a function to call the container when the user chosed to exit the editor (clicked the close button to navigate away from the editor)--> 		</jsBlock></javaScript> 	<notificationsAndRequests> 		<enableStatisticsRequests>1</enableStatisticsRequests> 		<enableReportErrorsRequests>1</enableReportErrorsRequests></notificationsAndRequests></uiConf>