<?xml version="1.0" encoding="UTF-8"?>
<database defaultPhpNamingMethod="underscore" heavyIndexing="false" name="propel" defaultIdMethod="native" package="plugins.reach"><table skipSql="false" abstract="false" name="vendor_catalog_item"><column primaryKey="true" required="true" autoIncrement="true" lazyLoad="false" name="id" type="integer"/><column primaryKey="false" required="true" autoIncrement="false" lazyLoad="false" name="name" type="varchar" size="256"/><column primaryKey="false" required="true" autoIncrement="false" lazyLoad="false" name="system_name" type="varchar" size="256"/><column primaryKey="false" required="false" autoIncrement="false" lazyLoad="false" name="created_at" type="timestamp"/><column primaryKey="false" required="false" autoIncrement="false" lazyLoad="false" name="updated_at" type="timestamp"/><column primaryKey="false" required="true" autoIncrement="false" lazyLoad="false" name="status" type="tinyint"/><column primaryKey="false" required="true" autoIncrement="false" lazyLoad="false" name="vendor_partner_id" type="integer"/><column primaryKey="false" required="true" autoIncrement="false" lazyLoad="false" name="service_type" type="tinyint"/><column primaryKey="false" required="true" autoIncrement="false" lazyLoad="false" name="service_feature" type="tinyint" inheritance="single"/><column primaryKey="false" required="true" autoIncrement="false" lazyLoad="false" name="turn_around_time" type="integer"/><column primaryKey="false" required="false" autoIncrement="false" lazyLoad="false" name="source_language" type="varchar" size="256"/><column primaryKey="false" required="false" autoIncrement="false" lazyLoad="false" name="target_language" type="varchar" size="256"/><column primaryKey="false" required="false" autoIncrement="false" lazyLoad="false" name="output_format" type="varchar" size="256"/><column primaryKey="false" required="false" autoIncrement="false" lazyLoad="false" name="custom_data" type="longvarchar"/><index name="status_service_type_index"><index-column name="status"/><index-column name="service_type"/></index><index name="status_service_type_service_feature_index"><index-column name="status"/><index-column name="service_type"/><index-column name="service_feature"/></index></table><table skipSql="false" abstract="false" name="partner_catalog_item"><column primaryKey="true" required="true" autoIncrement="true" lazyLoad="false" name="id" type="integer"/><column primaryKey="false" required="false" autoIncrement="false" lazyLoad="false" name="created_at" type="timestamp"/><column primaryKey="false" required="false" autoIncrement="false" lazyLoad="false" name="updated_at" type="timestamp"/><column primaryKey="false" required="true" autoIncrement="false" lazyLoad="false" name="status" type="tinyint"/><column primaryKey="false" required="true" autoIncrement="false" lazyLoad="false" name="partner_id" type="integer"/><column primaryKey="false" required="true" autoIncrement="false" lazyLoad="false" name="catalog_item_id" type="integer"/><column primaryKey="false" required="false" autoIncrement="false" lazyLoad="false" name="custom_data" type="longvarchar"/><index name="partner_id_status_index"><index-column name="partner_id"/><index-column name="status"/></index></table><table skipSql="false" abstract="false" name="reach_profile"><column primaryKey="true" required="true" autoIncrement="true" lazyLoad="false" name="id" type="integer"/><column primaryKey="false" required="false" autoIncrement="false" lazyLoad="false" name="name" type="varchar" size="256"/><column primaryKey="false" required="false" autoIncrement="false" lazyLoad="false" name="created_at" type="timestamp"/><column primaryKey="false" required="false" autoIncrement="false" lazyLoad="false" name="updated_at" type="timestamp"/><column primaryKey="false" required="true" autoIncrement="false" lazyLoad="false" name="partner_id" type="integer"/><column primaryKey="false" required="true" autoIncrement="false" lazyLoad="false" name="type" type="tinyint"/><column primaryKey="false" required="true" autoIncrement="false" lazyLoad="false" name="status" type="tinyint"/><column primaryKey="false" required="false" autoIncrement="false" lazyLoad="false" name="used_credit" type="integer" default="0"/><column primaryKey="false" required="false" autoIncrement="false" lazyLoad="false" name="rules" type="longvarchar"/><column primaryKey="false" required="false" autoIncrement="false" lazyLoad="false" name="dictionary" type="longvarchar"/><column primaryKey="false" required="false" autoIncrement="false" lazyLoad="false" name="custom_data" type="longvarchar"/><index name="partner_id_status_index"><index-column name="partner_id"/><index-column name="status"/></index><index name="partner_id_type_index"><index-column name="partner_id"/><index-column name="type"/></index></table><table skipSql="false" abstract="false" name="entry_vendor_task"><column primaryKey="true" required="true" autoIncrement="true" lazyLoad="false" name="id" type="bigint"/><column primaryKey="false" required="false" autoIncrement="false" lazyLoad="false" name="created_at" type="timestamp"/><column primaryKey="false" required="false" autoIncrement="false" lazyLoad="false" name="updated_at" type="timestamp"/><column primaryKey="false" required="false" autoIncrement="false" lazyLoad="false" name="queue_time" type="timestamp" default="null"/><column primaryKey="false" required="false" autoIncrement="false" lazyLoad="false" name="finish_time" type="timestamp" default="null"/><column primaryKey="false" required="true" autoIncrement="false" lazyLoad="false" name="partner_id" type="integer"/><column primaryKey="false" required="true" autoIncrement="false" lazyLoad="false" name="vendor_partner_id" type="integer"/><column primaryKey="false" required="true" autoIncrement="false" lazyLoad="false" name="entry_id" type="varchar" size="31"/><column primaryKey="false" required="true" autoIncrement="false" lazyLoad="false" name="status" type="tinyint"/><column primaryKey="false" required="true" autoIncrement="false" lazyLoad="false" name="price" type="integer"/><column primaryKey="false" required="true" autoIncrement="false" lazyLoad="false" name="catalog_item_id" type="integer"/><column primaryKey="false" required="true" autoIncrement="false" lazyLoad="false" name="reach_profile_id" type="integer"/><column primaryKey="false" required="true" autoIncrement="false" lazyLoad="false" name="kuser_id" type="integer"/><column primaryKey="false" required="false" autoIncrement="false" lazyLoad="false" name="version" type="integer"/><column primaryKey="false" required="false" autoIncrement="false" lazyLoad="false" name="context" type="varchar" size="256"/><column primaryKey="false" required="false" autoIncrement="false" lazyLoad="false" name="custom_data" type="longvarchar"/><index name="partner_id_status_index"><index-column name="partner_id"/><index-column name="status"/></index><index name="vendor_partner_id_status_index"><index-column name="vendor_partner_id"/><index-column name="status"/></index><index name="partner_entry_index"><index-column name="partner_id"/><index-column name="entry_id"/></index></table></database>
