[{"type":"KalturaAmazonS3StorageExportJobData","description":"","isAbstract":false,"isSimpleType":false,"isComplexType":true,"isFile":false,"isEnum":false,"isStringEnum":false,"isArray":false,"isReadOnly":false,"isInsertOnly":false,"isWriteOnly":false,"properties":[{"type":"string","name":"serverUrl","isSimpleType":true,"isComplexType":false,"isFile":false,"isEnum":false,"isStringEnum":false,"isArray":false,"isReadOnly":false,"isInsertOnly":false,"isWriteOnly":false,"description":""},{"type":"string","name":"serverUsername","isSimpleType":true,"isComplexType":false,"isFile":false,"isEnum":false,"isStringEnum":false,"isArray":false,"isReadOnly":false,"isInsertOnly":false,"isWriteOnly":false,"description":""},{"type":"string","name":"serverPassword","isSimpleType":true,"isComplexType":false,"isFile":false,"isEnum":false,"isStringEnum":false,"isArray":false,"isReadOnly":false,"isInsertOnly":false,"isWriteOnly":false,"description":""},{"type":"string","name":"serverPrivateKey","isSimpleType":true,"isComplexType":false,"isFile":false,"isEnum":false,"isStringEnum":false,"isArray":false,"isReadOnly":false,"isInsertOnly":false,"isWriteOnly":false,"description":""},{"type":"string","name":"serverPublicKey","isSimpleType":true,"isComplexType":false,"isFile":false,"isEnum":false,"isStringEnum":false,"isArray":false,"isReadOnly":false,"isInsertOnly":false,"isWriteOnly":false,"description":""},{"type":"string","name":"serverPassPhrase","isSimpleType":true,"isComplexType":false,"isFile":false,"isEnum":false,"isStringEnum":false,"isArray":false,"isReadOnly":false,"isInsertOnly":false,"isWriteOnly":false,"description":""},{"type":"bool","name":"ftpPassiveMode","isSimpleType":true,"isComplexType":false,"isFile":false,"isEnum":false,"isStringEnum":false,"isArray":false,"isReadOnly":false,"isInsertOnly":false,"isWriteOnly":false,"description":""},{"type":"string","name":"srcFileSyncLocalPath","isSimpleType":true,"isComplexType":false,"isFile":false,"isEnum":false,"isStringEnum":false,"isArray":false,"isReadOnly":false,"isInsertOnly":false,"isWriteOnly":false,"description":""},{"type":"string","name":"srcFileSyncId","isSimpleType":true,"isComplexType":false,"isFile":false,"isEnum":false,"isStringEnum":false,"isArray":false,"isReadOnly":false,"isInsertOnly":false,"isWriteOnly":false,"description":""},{"type":"string","name":"destFileSyncStoredPath","isSimpleType":true,"isComplexType":false,"isFile":false,"isEnum":false,"isStringEnum":false,"isArray":false,"isReadOnly":false,"isInsertOnly":false,"isWriteOnly":false,"description":""},{"type":"bool","name":"force","isSimpleType":true,"isComplexType":false,"isFile":false,"isEnum":false,"isStringEnum":false,"isArray":false,"isReadOnly":false,"isInsertOnly":false,"isWriteOnly":false,"description":""},{"type":"bool","name":"createLink","isSimpleType":true,"isComplexType":false,"isFile":false,"isEnum":false,"isStringEnum":false,"isArray":false,"isReadOnly":false,"isInsertOnly":false,"isWriteOnly":false,"description":""},{"type":"string","name":"filesPermissionInS3","isSimpleType":true,"isComplexType":true,"isFile":false,"isEnum":true,"isStringEnum":true,"isArray":false,"isReadOnly":false,"isInsertOnly":false,"isWriteOnly":false,"description":"","constants":[{"type":"string","name":"ACL_AUTHENTICATED_READ","defaultValue":"authenticated-read","description":"","isSimpleType":true},{"type":"string","name":"ACL_PRIVATE","defaultValue":"private","description":"","isSimpleType":true},{"type":"string","name":"ACL_PUBLIC_READ","defaultValue":"public-read","description":"","isSimpleType":true},{"type":"string","name":"ACL_PUBLIC_READ_WRITE","defaultValue":"public-read-write","description":"","isSimpleType":true}]},{"type":"string","name":"s3Region","isSimpleType":true,"isComplexType":false,"isFile":false,"isEnum":false,"isStringEnum":false,"isArray":false,"isReadOnly":false,"isInsertOnly":false,"isWriteOnly":false,"description":""}]},{"type":"KalturaKontikiStorageExportJobData","description":"","isAbstract":false,"isSimpleType":false,"isComplexType":true,"isFile":false,"isEnum":false,"isStringEnum":false,"isArray":false,"isReadOnly":false,"isInsertOnly":false,"isWriteOnly":false,"properties":[{"type":"string","name":"serverUrl","isSimpleType":true,"isComplexType":false,"isFile":false,"isEnum":false,"isStringEnum":false,"isArray":false,"isReadOnly":false,"isInsertOnly":false,"isWriteOnly":false,"description":""},{"type":"string","name":"serverUsername","isSimpleType":true,"isComplexType":false,"isFile":false,"isEnum":false,"isStringEnum":false,"isArray":false,"isReadOnly":false,"isInsertOnly":false,"isWriteOnly":false,"description":""},{"type":"string","name":"serverPassword","isSimpleType":true,"isComplexType":false,"isFile":false,"isEnum":false,"isStringEnum":false,"isArray":false,"isReadOnly":false,"isInsertOnly":false,"isWriteOnly":false,"description":""},{"type":"string","name":"serverPrivateKey","isSimpleType":true,"isComplexType":false,"isFile":false,"isEnum":false,"isStringEnum":false,"isArray":false,"isReadOnly":false,"isInsertOnly":false,"isWriteOnly":false,"description":""},{"type":"string","name":"serverPublicKey","isSimpleType":true,"isComplexType":false,"isFile":false,"isEnum":false,"isStringEnum":false,"isArray":false,"isReadOnly":false,"isInsertOnly":false,"isWriteOnly":false,"description":""},{"type":"string","name":"serverPassPhrase","isSimpleType":true,"isComplexType":false,"isFile":false,"isEnum":false,"isStringEnum":false,"isArray":false,"isReadOnly":false,"isInsertOnly":false,"isWriteOnly":false,"description":""},{"type":"bool","name":"ftpPassiveMode","isSimpleType":true,"isComplexType":false,"isFile":false,"isEnum":false,"isStringEnum":false,"isArray":false,"isReadOnly":false,"isInsertOnly":false,"isWriteOnly":false,"description":""},{"type":"string","name":"srcFileSyncLocalPath","isSimpleType":true,"isComplexType":false,"isFile":false,"isEnum":false,"isStringEnum":false,"isArray":false,"isReadOnly":false,"isInsertOnly":false,"isWriteOnly":false,"description":""},{"type":"string","name":"srcFileSyncId","isSimpleType":true,"isComplexType":false,"isFile":false,"isEnum":false,"isStringEnum":false,"isArray":false,"isReadOnly":false,"isInsertOnly":false,"isWriteOnly":false,"description":""},{"type":"string","name":"destFileSyncStoredPath","isSimpleType":true,"isComplexType":false,"isFile":false,"isEnum":false,"isStringEnum":false,"isArray":false,"isReadOnly":false,"isInsertOnly":false,"isWriteOnly":false,"description":""},{"type":"bool","name":"force","isSimpleType":true,"isComplexType":false,"isFile":false,"isEnum":false,"isStringEnum":false,"isArray":false,"isReadOnly":false,"isInsertOnly":false,"isWriteOnly":false,"description":""},{"type":"bool","name":"createLink","isSimpleType":true,"isComplexType":false,"isFile":false,"isEnum":false,"isStringEnum":false,"isArray":false,"isReadOnly":false,"isInsertOnly":false,"isWriteOnly":false,"description":""},{"type":"string","name":"flavorAssetId","isSimpleType":true,"isComplexType":false,"isFile":false,"isEnum":false,"isStringEnum":false,"isArray":false,"isReadOnly":false,"isInsertOnly":false,"isWriteOnly":false,"description":"Holds the id of the exported asset"},{"type":"string","name":"contentMoid","isSimpleType":true,"isComplexType":false,"isFile":false,"isEnum":false,"isStringEnum":false,"isArray":false,"isReadOnly":false,"isInsertOnly":false,"isWriteOnly":false,"description":"Unique Kontiki MOID for the content uploaded to Kontiki"},{"type":"string","name":"serviceToken","isSimpleType":true,"isComplexType":false,"isFile":false,"isEnum":false,"isStringEnum":false,"isArray":false,"isReadOnly":false,"isInsertOnly":false,"isWriteOnly":false,"description":""}]}]