[{"type":"KalturaClipAttributes","description":"Clip operation attributes","isAbstract":false,"isSimpleType":false,"isComplexType":true,"isFile":false,"isEnum":false,"isStringEnum":false,"isArray":false,"isReadOnly":false,"isInsertOnly":false,"isWriteOnly":false,"properties":[{"type":"int","name":"offset","isSimpleType":true,"isComplexType":false,"isFile":false,"isEnum":false,"isStringEnum":false,"isArray":false,"isReadOnly":false,"isInsertOnly":false,"isWriteOnly":false,"description":"Offset in milliseconds"},{"type":"int","name":"duration","isSimpleType":true,"isComplexType":false,"isFile":false,"isEnum":false,"isStringEnum":false,"isArray":false,"isReadOnly":false,"isInsertOnly":false,"isWriteOnly":false,"description":"Duration in milliseconds"}]},{"type":"KalturaConcatAttributes","description":"Concat operation attributes","isAbstract":false,"isSimpleType":false,"isComplexType":true,"isFile":false,"isEnum":false,"isStringEnum":false,"isArray":false,"isReadOnly":false,"isInsertOnly":false,"isWriteOnly":false,"properties":[{"type":"KalturaDataCenterContentResource","name":"resource","isSimpleType":false,"isComplexType":true,"isFile":false,"isEnum":false,"isStringEnum":false,"isArray":false,"isReadOnly":false,"isInsertOnly":false,"isWriteOnly":false,"description":"The resource to be concatenated","properties":[]}]}]